voyapt/__init__.py
voyapt/core.py
voyapt/geojson.py
voyapt/plotting.py
voyapt/statistics.py
voyapt-0.1.0.dev0.dist-info/METADATA
voyapt-0.1.0.dev0.dist-info/WHEEL
voyapt-0.1.0.dev0.dist-info/top_level.txt
voyapt-0.1.0.dev0.dist-info/RECORD
